[
    {
        "clave": "70650005",
        "nombre": "Alfonso Corona del Rosal"
    },
    {
        "clave": "70650008",
        "nombre": "La Asunción"
    },
    {
        "clave": "70650046",
        "nombre": "El Desengaño (La Montaña)"
    },
    {
        "clave": "70650052",
        "nombre": "Nueva Galilea"
    },
    {
        "clave": "70650066",
        "nombre": "Los Llanos"
    },
    {
        "clave": "70650097",
        "nombre": "La Providencia"
    },
    {
        "clave": "70650182",
        "nombre": "Agua Blanca Serranía"
    },
    {
        "clave": "70650184",
        "nombre": "Profesor Roberto Barrios"
    },
    {
        "clave": "70650190",
        "nombre": "El Lacandón"
    },
    {
        "clave": "70650191",
        "nombre": "Arimatea"
    },
    {
        "clave": "70650199",
        "nombre": "Venustiano Carranza"
    },
    {
        "clave": "70650205",
        "nombre": "La Flor de Chiapas"
    },
    {
        "clave": "70650208",
        "nombre": "Nuevo Jalisco Osumacinta"
    },
    {
        "clave": "70650211",
        "nombre": "Augusto Gómez Villanueva"
    },
    {
        "clave": "70650220",
        "nombre": "El Desierto"
    },
    {
        "clave": "70650255",
        "nombre": "Santa Rosa"
    },
    {
        "clave": "70650258",
        "nombre": "Ampliación Palenque"
    },
    {
        "clave": "70650304",
        "nombre": "El Porvenir"
    },
    {
        "clave": "70650352",
        "nombre": "División del Norte"
    },
    {
        "clave": "70650354",
        "nombre": "San José la Unión"
    },
    {
        "clave": "70650376",
        "nombre": "Campo Lencho"
    },
    {
        "clave": "70650428",
        "nombre": "El Palmar"
    },
    {
        "clave": "70650430",
        "nombre": "Santa Rosa Uno"
    },
    {
        "clave": "70650441",
        "nombre": "La Carmelita"
    },
    {
        "clave": "70650452",
        "nombre": "Santa Cruz"
    },
    {
        "clave": "70650457",
        "nombre": "Acapulquito"
    },
    {
        "clave": "70650478",
        "nombre": "Ampliación 2da. Emilio Rabasa"
    },
    {
        "clave": "70650479",
        "nombre": "San Luis 1ra. Sección"
    },
    {
        "clave": "70650502",
        "nombre": "Azteca"
    },
    {
        "clave": "70650509",
        "nombre": "La Caoba"
    },
    {
        "clave": "70650512",
        "nombre": "Toniná"
    },
    {
        "clave": "70650514",
        "nombre": "La Loma"
    },
    {
        "clave": "70650539",
        "nombre": "Puente Michol (Key)"
    },
    {
        "clave": "70650598",
        "nombre": "Nuevo Egipto"
    },
    {
        "clave": "70650602",
        "nombre": "Nueva Central"
    },
    {
        "clave": "70650606",
        "nombre": "Niños Héroes"
    },
    {
        "clave": "70650612",
        "nombre": "Pueblo Nuevo Usumacinta"
    },
    {
        "clave": "70650625",
        "nombre": "José María Morelos y Pavón"
    },
    {
        "clave": "70650626",
        "nombre": "Nuevo Retiro"
    },
    {
        "clave": "70650627",
        "nombre": "Netzahualcóyotl"
    },
    {
        "clave": "70650638",
        "nombre": "San Lorenzo (Chocoljá)"
    },
    {
        "clave": "70650639",
        "nombre": "Ricardo Flores Magón"
    },
    {
        "clave": "70650640",
        "nombre": "La Calandria"
    },
    {
        "clave": "70650657",
        "nombre": "Antioquía"
    },
    {
        "clave": "70650661",
        "nombre": "La Esperanza"
    },
    {
        "clave": "70650665",
        "nombre": "San José del Carmen (El Bascancito)"
    },
    {
        "clave": "70650678",
        "nombre": "San Antonio (La Sombra)"
    },
    {
        "clave": "70650694",
        "nombre": "El Emporio"
    },
    {
        "clave": "70650712",
        "nombre": "San Juan Tulija (San Juan)"
    },
    {
        "clave": "70650813",
        "nombre": "Montecristo"
    },
    {
        "clave": "70650961",
        "nombre": "San Javier 2da. Sección"
    },
    {
        "clave": "70651007",
        "nombre": "El Naranjal"
    },
    {
        "clave": "70651011",
        "nombre": "Monte Olivo"
    },
    {
        "clave": "70651012",
        "nombre": "Flor del Río"
    },
    {
        "clave": "70651032",
        "nombre": "Eben Ezer"
    },
    {
        "clave": "70651037",
        "nombre": "Bitalo"
    },
    {
        "clave": "70651048",
        "nombre": "El Rincón del Guano"
    },
    {
        "clave": "70651052",
        "nombre": "El Chinal"
    },
    {
        "clave": "70651081",
        "nombre": "Los Gómez"
    },
    {
        "clave": "70651096",
        "nombre": "La Ensenada Chutalijá"
    },
    {
        "clave": "70651156",
        "nombre": "San Antonio"
    },
    {
        "clave": "70651170",
        "nombre": "San José"
    },
    {
        "clave": "70651177",
        "nombre": "San Miguel Arimatea"
    },
    {
        "clave": "70651230",
        "nombre": "Arroyo Jerusalén"
    },
    {
        "clave": "70651232",
        "nombre": "Margarita Maza de Juárez"
    },
    {
        "clave": "70651239",
        "nombre": "Ach'Lum Maya"
    },
    {
        "clave": "70651259",
        "nombre": "Escuintla"
    },
    {
        "clave": "70651260",
        "nombre": "Nuevo Suclumpá"
    },
    {
        "clave": "70651278",
        "nombre": "Ach'Lum San Marcos"
    },
    {
        "clave": "70651282",
        "nombre": "General Emiliano Zapata"
    },
    {
        "clave": "70651283",
        "nombre": "Estrella de Belén"
    },
    {
        "clave": "70651289",
        "nombre": "Los Olvidados"
    },
    {
        "clave": "70651295",
        "nombre": "San Simión"
    },
    {
        "clave": "70651301",
        "nombre": "20 de Febrero"
    },
    {
        "clave": "70651302",
        "nombre": "Victoria Campesina I"
    },
    {
        "clave": "70651304",
        "nombre": "Agua Cristalina"
    },
    {
        "clave": "70651305",
        "nombre": "Los Ángeles"
    },
    {
        "clave": "70651307",
        "nombre": "Doctor Manuel Velasco Suárez"
    },
    {
        "clave": "70651308",
        "nombre": "El Espejo"
    },
    {
        "clave": "70651309",
        "nombre": "La Guadalupe"
    },
    {
        "clave": "70651310",
        "nombre": "Jericó 2da. Sección"
    },
    {
        "clave": "70651311",
        "nombre": "Lindavista Xinich"
    },
    {
        "clave": "70651314",
        "nombre": "Nueva Jerusalén (El Jaguar)"
    },
    {
        "clave": "70651315",
        "nombre": "Nueva Jerusalén de la Montaña"
    },
    {
        "clave": "70651317",
        "nombre": "Montebello"
    },
    {
        "clave": "70651318",
        "nombre": "Nuevo Taniperla"
    },
    {
        "clave": "70651321",
        "nombre": "Nuevo Altamirano"
    },
    {
        "clave": "70651323",
        "nombre": "Unidad y Trabajo"
    },
    {
        "clave": "70651324",
        "nombre": "Río Osumacinta"
    },
    {
        "clave": "70651335",
        "nombre": "20 de Junio"
    },
    {
        "clave": "70651342",
        "nombre": "San Marcos 2da. Sección"
    },
    {
        "clave": "70651343",
        "nombre": "Santa Isabel"
    },
    {
        "clave": "70651348",
        "nombre": "Los Girasoles"
    },
    {
        "clave": "70651351",
        "nombre": "El Limonar"
    },
    {
        "clave": "70651355",
        "nombre": "El Palmar"
    },
    {
        "clave": "70651357",
        "nombre": "El Pital Uno"
    },
    {
        "clave": "70651372",
        "nombre": "El Guayacán"
    },
    {
        "clave": "70651374",
        "nombre": "La Hacienda"
    },
    {
        "clave": "70651375",
        "nombre": "Alfredo V. Bonfil"
    },
    {
        "clave": "70651376",
        "nombre": "Arroyo Encanto II"
    },
    {
        "clave": "70651377",
        "nombre": "El Campito"
    },
    {
        "clave": "70651378",
        "nombre": "La Alianza"
    },
    {
        "clave": "70651380",
        "nombre": "San Juan el Sacrificio"
    },
    {
        "clave": "70651381",
        "nombre": "San Marcos"
    },
    {
        "clave": "70651389",
        "nombre": "San José Chancala 2da.Sección"
    },
    {
        "clave": "70651394",
        "nombre": "La Nueva Fortuna"
    },
    {
        "clave": "70651395",
        "nombre": "Lázaro Cárdenas"
    },
    {
        "clave": "70651400",
        "nombre": "San Vicente"
    },
    {
        "clave": "70651407",
        "nombre": "Rosa Blanca"
    },
    {
        "clave": "70651408",
        "nombre": "Generación 2000"
    },
    {
        "clave": "70651409",
        "nombre": "San Marcos II Sección"
    },
    {
        "clave": "70651411",
        "nombre": "La Fortuna"
    },
    {
        "clave": "70651413",
        "nombre": "Las Gardenias"
    },
    {
        "clave": "70651416",
        "nombre": "La Revolución"
    },
    {
        "clave": "70650003",
        "nombre": "El Aguacate"
    },
    {
        "clave": "70650007",
        "nombre": "Ángel Albino Corzo 1ra. Sección"
    },
    {
        "clave": "70650009",
        "nombre": "La Aurora"
    },
    {
        "clave": "70650010",
        "nombre": "Babilonia 1ra. Sección"
    },
    {
        "clave": "70650011",
        "nombre": "Bajadas Grandes"
    },
    {
        "clave": "70650012",
        "nombre": "El Barí"
    },
    {
        "clave": "70650013",
        "nombre": "Belisario Domínguez Norte"
    },
    {
        "clave": "70650014",
        "nombre": "Berea"
    },
    {
        "clave": "70650015",
        "nombre": "Boca de Chancala"
    },
    {
        "clave": "70650018",
        "nombre": "Calatraba"
    },
    {
        "clave": "70650019",
        "nombre": "El Cambio"
    },
    {
        "clave": "70650023",
        "nombre": "La Cascada"
    },
    {
        "clave": "70650024",
        "nombre": "Los Cerrillos"
    },
    {
        "clave": "70650026",
        "nombre": "5 de Mayo"
    },
    {
        "clave": "70650027",
        "nombre": "Ciudad Agraria"
    },
    {
        "clave": "70650028",
        "nombre": "El Clavo"
    },
    {
        "clave": "70650034",
        "nombre": "Chacamax"
    },
    {
        "clave": "70650035",
        "nombre": "Estación Chacamax"
    },
    {
        "clave": "70650038",
        "nombre": "Chancala Río Seco"
    },
    {
        "clave": "70650040",
        "nombre": "El Chinal"
    },
    {
        "clave": "70650042",
        "nombre": "San Antonio Chuyipá"
    },
    {
        "clave": "70650043",
        "nombre": "Las Delicias"
    },
    {
        "clave": "70650047",
        "nombre": "El Edén"
    },
    {
        "clave": "70650048",
        "nombre": "Emiliano Zapata"
    },
    {
        "clave": "70650051",
        "nombre": "Francisco I. Madero Norte"
    },
    {
        "clave": "70650053",
        "nombre": "La Gloria"
    },
    {
        "clave": "70650055",
        "nombre": "Graciano Sánchez"
    },
    {
        "clave": "70650057",
        "nombre": "Licenciado Gustavo Díaz Ordaz"
    },
    {
        "clave": "70650058",
        "nombre": "Hermenegildo Galeana"
    },
    {
        "clave": "70650060",
        "nombre": "Licenciado José Castillo Tielmans"
    },
    {
        "clave": "70650061",
        "nombre": "San José (Osumacinta)"
    },
    {
        "clave": "70650063",
        "nombre": "Lázaro Cárdenas"
    },
    {
        "clave": "70650064",
        "nombre": "Lindavista (Chiniquija)"
    },
    {
        "clave": "70650068",
        "nombre": "Medellín 2da. Sección"
    },
    {
        "clave": "70650074",
        "nombre": "El Naranjo"
    },
    {
        "clave": "70650076",
        "nombre": "Nueva Betania"
    },
    {
        "clave": "70650077",
        "nombre": "Nueva Esperanza 1ra. Sección"
    },
    {
        "clave": "70650080",
        "nombre": "Nuevo Mérida"
    },
    {
        "clave": "70650082",
        "nombre": "Nuevo Yajalón"
    },
    {
        "clave": "70650083",
        "nombre": "Álvaro Obregón"
    },
    {
        "clave": "70650086",
        "nombre": "El Palmar 2da. Sección"
    },
    {
        "clave": "70650091",
        "nombre": "Portaceli"
    },
    {
        "clave": "70650095",
        "nombre": "La Primavera"
    },
    {
        "clave": "70650096",
        "nombre": "El Progreso"
    },
    {
        "clave": "70650098",
        "nombre": "Puyipa"
    },
    {
        "clave": "70650103",
        "nombre": "El Retiro"
    },
    {
        "clave": "70650105",
        "nombre": "Río Chancalá"
    },
    {
        "clave": "70650106",
        "nombre": "Doctor Samuel León Brindis"
    },
    {
        "clave": "70650108",
        "nombre": "San Antonio el Potrero"
    },
    {
        "clave": "70650112",
        "nombre": "San Francisco Palenque"
    },
    {
        "clave": "70650114",
        "nombre": "Nuevo San Joaquín"
    },
    {
        "clave": "70650118",
        "nombre": "Babilonia"
    },
    {
        "clave": "70650119",
        "nombre": "San José Chancala Primera Sección"
    },
    {
        "clave": "70650123",
        "nombre": "San Juan Chancalaíto"
    },
    {
        "clave": "70650126",
        "nombre": "San Manuel"
    },
    {
        "clave": "70650129",
        "nombre": "San Marcos"
    },
    {
        "clave": "70650131",
        "nombre": "San Martín Chamizal"
    },
    {
        "clave": "70650132",
        "nombre": "San Mateo"
    },
    {
        "clave": "70650134",
        "nombre": "San Pedro"
    },
    {
        "clave": "70650138",
        "nombre": "Santa Cruz"
    },
    {
        "clave": "70650145",
        "nombre": "Tomás Garrido Canabal"
    },
    {
        "clave": "70650149",
        "nombre": "Poblado la Unión"
    },
    {
        "clave": "70650151",
        "nombre": "Úrsulo Galván"
    },
    {
        "clave": "70650153",
        "nombre": "20 de Noviembre"
    },
    {
        "clave": "70650156",
        "nombre": "La Victoria"
    },
    {
        "clave": "70650161",
        "nombre": "Zapatero"
    },
    {
        "clave": "70650164",
        "nombre": "La Ponderosa"
    },
    {
        "clave": "70650169",
        "nombre": "Luis I. Cabrera (Tepezcuintle)"
    },
    {
        "clave": "70650171",
        "nombre": "Tzeltal Mukul-Já"
    },
    {
        "clave": "70650183",
        "nombre": "Benito Juárez"
    },
    {
        "clave": "70650187",
        "nombre": "Miguel Hidalgo (Estación Lacandón)"
    },
    {
        "clave": "70650188",
        "nombre": "Adolfo López Mateos"
    },
    {
        "clave": "70650192",
        "nombre": "Belén"
    },
    {
        "clave": "70650196",
        "nombre": "Saturnino Ríos"
    },
    {
        "clave": "70650198",
        "nombre": "Chancala Zapote"
    },
    {
        "clave": "70650201",
        "nombre": "Emilio Rabasa"
    },
    {
        "clave": "70650207",
        "nombre": "La Caoba"
    },
    {
        "clave": "70650209",
        "nombre": "Vistahermosa"
    },
    {
        "clave": "70650210",
        "nombre": "Victórico Grajales"
    },
    {
        "clave": "70650215",
        "nombre": "Ricardo Flores Magón"
    },
    {
        "clave": "70650216",
        "nombre": "Once de Julio"
    },
    {
        "clave": "70650218",
        "nombre": "El Sinaí"
    },
    {
        "clave": "70650219",
        "nombre": "El Mango"
    },
    {
        "clave": "70650223",
        "nombre": "Francisco Villa"
    },
    {
        "clave": "70650224",
        "nombre": "Nuevo Sonora"
    },
    {
        "clave": "70650226",
        "nombre": "Río San Diego"
    },
    {
        "clave": "70650267",
        "nombre": "Colonia González"
    },
    {
        "clave": "70650269",
        "nombre": "La Espuela"
    },
    {
        "clave": "70650273",
        "nombre": "Nuevo León"
    },
    {
        "clave": "70650294",
        "nombre": "El Naranjal"
    },
    {
        "clave": "70650297",
        "nombre": "Guadalupe"
    },
    {
        "clave": "70650305",
        "nombre": "Chacamax"
    },
    {
        "clave": "70650308",
        "nombre": "Ejido Palenque"
    },
    {
        "clave": "70650312",
        "nombre": "San Rafael"
    },
    {
        "clave": "70650323",
        "nombre": "Nuevo Jalapa"
    },
    {
        "clave": "70650335",
        "nombre": "La Esperanza"
    },
    {
        "clave": "70650343",
        "nombre": "Cinco de Mayo"
    },
    {
        "clave": "70650349",
        "nombre": "San Juan Bautista"
    },
    {
        "clave": "70650351",
        "nombre": "El Limón"
    },
    {
        "clave": "70650356",
        "nombre": "La Guadalupe"
    },
    {
        "clave": "70650367",
        "nombre": "San Luis"
    },
    {
        "clave": "70650368",
        "nombre": "San Luis Chico"
    },
    {
        "clave": "70650382",
        "nombre": "Santa Isabel"
    },
    {
        "clave": "70650389",
        "nombre": "Pueblo Nuevo"
    },
    {
        "clave": "70650393",
        "nombre": "San Luis 2da. Sección"
    },
    {
        "clave": "70650399",
        "nombre": "Nuevo Paraíso"
    },
    {
        "clave": "70650408",
        "nombre": "San Miguel"
    },
    {
        "clave": "70650420",
        "nombre": "San José"
    },
    {
        "clave": "70650427",
        "nombre": "Medellín 1ra. Sección"
    },
    {
        "clave": "70650429",
        "nombre": "El Palmar 1ra. Sección"
    },
    {
        "clave": "70650439",
        "nombre": "El Sacrificio"
    },
    {
        "clave": "70650480",
        "nombre": "La Nueva Unión"
    },
    {
        "clave": "70650486",
        "nombre": "Estación San Agustín (La Placa)"
    },
    {
        "clave": "70650497",
        "nombre": "Nuevo Mérida 2da. Sección"
    },
    {
        "clave": "70650503",
        "nombre": "Azcapotzalco"
    },
    {
        "clave": "70650517",
        "nombre": "San Francisco las Ruinas"
    },
    {
        "clave": "70650518",
        "nombre": "Santa Cruz Uno"
    },
    {
        "clave": "70650549",
        "nombre": "El Guayacán"
    },
    {
        "clave": "70650574",
        "nombre": "El Nopal"
    },
    {
        "clave": "70650575",
        "nombre": "El Esquinero"
    },
    {
        "clave": "70650586",
        "nombre": "San Francisco Chancala"
    },
    {
        "clave": "70650587",
        "nombre": "El Tenampa"
    },
    {
        "clave": "70650599",
        "nombre": "Brillante Buenavista"
    },
    {
        "clave": "70650605",
        "nombre": "Los Aguilares"
    },
    {
        "clave": "70650608",
        "nombre": "San José"
    },
    {
        "clave": "70650609",
        "nombre": "Chocoljaíto"
    },
    {
        "clave": "70650610",
        "nombre": "La Reforma de Ocampo"
    },
    {
        "clave": "70650621",
        "nombre": "Arroyo Belén"
    },
    {
        "clave": "70650622",
        "nombre": "El Sacrificio"
    },
    {
        "clave": "70650628",
        "nombre": "Dos Arbolitos"
    },
    {
        "clave": "70650631",
        "nombre": "Once de Julio 2da. Sección (Macedonia)"
    },
    {
        "clave": "70650660",
        "nombre": "El Chinal"
    },
    {
        "clave": "70650683",
        "nombre": "Ángel Albino Corzo 2da. Sección"
    },
    {
        "clave": "70650685",
        "nombre": "Cuauhtémoc Chancala (El Guanal)"
    },
    {
        "clave": "70650688",
        "nombre": "Nueva Esperanza 2da. Sección"
    },
    {
        "clave": "70650692",
        "nombre": "San Simón"
    },
    {
        "clave": "70650704",
        "nombre": "Poblado Nuevo Arroyo"
    },
    {
        "clave": "70650708",
        "nombre": "La Gloria"
    },
    {
        "clave": "70650720",
        "nombre": "San José"
    },
    {
        "clave": "70650721",
        "nombre": "Ricardo Flores Magón"
    },
    {
        "clave": "70650724",
        "nombre": "Seis Hermanas"
    },
    {
        "clave": "70650731",
        "nombre": "Miguel Hidalgo"
    },
    {
        "clave": "70650772",
        "nombre": "Agua Escondida"
    },
    {
        "clave": "70650773",
        "nombre": "Lomas Tristes"
    },
    {
        "clave": "70650775",
        "nombre": "La Escondida"
    },
    {
        "clave": "70650793",
        "nombre": "Tres Hermanos"
    },
    {
        "clave": "70650817",
        "nombre": "Galileo"
    },
    {
        "clave": "70650818",
        "nombre": "La Primavera"
    },
    {
        "clave": "70650930",
        "nombre": "El Barrial"
    },
    {
        "clave": "70650950",
        "nombre": "Nuevo Laredo"
    },
    {
        "clave": "70650963",
        "nombre": "El Palomar"
    },
    {
        "clave": "70650977",
        "nombre": "El Niño Perdido"
    },
    {
        "clave": "70650987",
        "nombre": "El Desengaño"
    },
    {
        "clave": "70650991",
        "nombre": "San Pedro"
    },
    {
        "clave": "70651022",
        "nombre": "Babilonia 3ra. Sección"
    },
    {
        "clave": "70651031",
        "nombre": "Ampliación Benito Juárez"
    },
    {
        "clave": "70651034",
        "nombre": "Agua Santa II"
    },
    {
        "clave": "70651054",
        "nombre": "El Chorrito"
    },
    {
        "clave": "70651060",
        "nombre": "General Emiliano Zapata del Valle"
    },
    {
        "clave": "70651061",
        "nombre": "Juan Sabines Guerrero"
    },
    {
        "clave": "70651073",
        "nombre": "Fracción San José"
    },
    {
        "clave": "70651074",
        "nombre": "San Javier"
    },
    {
        "clave": "70651103",
        "nombre": "Santa Cruz"
    },
    {
        "clave": "70651109",
        "nombre": "Monte de Sión"
    },
    {
        "clave": "70651111",
        "nombre": "Nueva Esperanza Progresista"
    },
    {
        "clave": "70651112",
        "nombre": "Nueva Independencia"
    },
    {
        "clave": "70651113",
        "nombre": "Nuevo Palenque"
    },
    {
        "clave": "70651131",
        "nombre": "El Porvenir [Vivero]"
    },
    {
        "clave": "70651144",
        "nombre": "La Revolución"
    },
    {
        "clave": "70651145",
        "nombre": "Cuauhtémoc Cárdenas"
    },
    {
        "clave": "70651146",
        "nombre": "La Rueda"
    },
    {
        "clave": "70651151",
        "nombre": "Nuevo Samaritano"
    },
    {
        "clave": "70651173",
        "nombre": "San Luis"
    },
    {
        "clave": "70651201",
        "nombre": "Las Delicias 2da. Sección"
    },
    {
        "clave": "70651222",
        "nombre": "El Tucán"
    },
    {
        "clave": "70651225",
        "nombre": "30 de Marzo (El Vergel)"
    },
    {
        "clave": "70651228",
        "nombre": "Zaragoza (Los Cerrillos)"
    },
    {
        "clave": "70651240",
        "nombre": "Adolfo López Mateos 2da. Sección"
    },
    {
        "clave": "70651242",
        "nombre": "El Aventurero"
    },
    {
        "clave": "70651243",
        "nombre": "El Bascán 2da. Sección"
    },
    {
        "clave": "70651244",
        "nombre": "Camino Real"
    },
    {
        "clave": "70651248",
        "nombre": "La Esperanza"
    },
    {
        "clave": "70651250",
        "nombre": "La Fortuna"
    },
    {
        "clave": "70651252",
        "nombre": "Francisco Villa"
    },
    {
        "clave": "70651256",
        "nombre": "Laguna Emiliano Zapata"
    },
    {
        "clave": "70651268",
        "nombre": "Santa Lúcia"
    },
    {
        "clave": "70651277",
        "nombre": "Las Tres Hermanas"
    },
    {
        "clave": "70651279",
        "nombre": "Agua Fría 2da. Sección"
    },
    {
        "clave": "70651286",
        "nombre": "La Joya"
    },
    {
        "clave": "70651287",
        "nombre": "Kilómetro 20"
    },
    {
        "clave": "70651291",
        "nombre": "Nuevo Plan de Ayala"
    },
    {
        "clave": "70651296",
        "nombre": "Santa Martha"
    },
    {
        "clave": "70651297",
        "nombre": "Santa María 2da. Sección"
    },
    {
        "clave": "70651303",
        "nombre": "30 de Marzo"
    },
    {
        "clave": "70651316",
        "nombre": "Nuevo Jericó"
    },
    {
        "clave": "70651336",
        "nombre": "Filadelfia"
    },
    {
        "clave": "70651337",
        "nombre": "General Felipe Ángeles"
    },
    {
        "clave": "70651344",
        "nombre": "Nuevo México"
    },
    {
        "clave": "70651379",
        "nombre": "Nuevo Montes Azules"
    },
    {
        "clave": "70651417",
        "nombre": "La Cumbre"
    },
    {
        "clave": "70651422",
        "nombre": "Luis Alfredo"
    },
    {
        "clave": "70650001",
        "nombre": "Palenque"
    },
    {
        "clave": "70650004",
        "nombre": "Agua Fría"
    },
    {
        "clave": "70650006",
        "nombre": "La América"
    },
    {
        "clave": "70650032",
        "nombre": "Las Cruces"
    },
    {
        "clave": "70650062",
        "nombre": "Jucuté"
    },
    {
        "clave": "70650067",
        "nombre": "Manga de Clavo"
    },
    {
        "clave": "70650069",
        "nombre": "La Bellota"
    },
    {
        "clave": "70650072",
        "nombre": "Monterrey"
    },
    {
        "clave": "70650075",
        "nombre": "El Naranjo"
    },
    {
        "clave": "70650084",
        "nombre": "Ojo de Agua"
    },
    {
        "clave": "70650092",
        "nombre": "El Porvenir"
    },
    {
        "clave": "70650094",
        "nombre": "El Porvenir Dos"
    },
    {
        "clave": "70650099",
        "nombre": "Ramalaso"
    },
    {
        "clave": "70650100",
        "nombre": "Raymundo Enríquez"
    },
    {
        "clave": "70650101",
        "nombre": "Reforma Agraria (Chiniquija)"
    },
    {
        "clave": "70650107",
        "nombre": "San Antonio"
    },
    {
        "clave": "70650110",
        "nombre": "San Felipe"
    },
    {
        "clave": "70650111",
        "nombre": "San Francisco"
    },
    {
        "clave": "70650122",
        "nombre": "San Rafael"
    },
    {
        "clave": "70650139",
        "nombre": "Santa Fe"
    },
    {
        "clave": "70650144",
        "nombre": "San Antonio (La suiza)"
    },
    {
        "clave": "70650150",
        "nombre": "Estación la Unión"
    },
    {
        "clave": "70650167",
        "nombre": "San José (Rumbo Perdido)"
    },
    {
        "clave": "70650168",
        "nombre": "La Pita"
    },
    {
        "clave": "70650175",
        "nombre": "San Juan"
    },
    {
        "clave": "70650186",
        "nombre": "San Marcos"
    },
    {
        "clave": "70650195",
        "nombre": "El Sacrificio"
    },
    {
        "clave": "70650249",
        "nombre": "Monte Quemado"
    },
    {
        "clave": "70650251",
        "nombre": "Nuevo Progreso"
    },
    {
        "clave": "70650252",
        "nombre": "Santa Yoli"
    },
    {
        "clave": "70650253",
        "nombre": "El Vaquero"
    },
    {
        "clave": "70650254",
        "nombre": "Púlinte"
    },
    {
        "clave": "70650256",
        "nombre": "La Hacienda"
    },
    {
        "clave": "70650257",
        "nombre": "El Guayacán"
    },
    {
        "clave": "70650261",
        "nombre": "La Guadalupe (Los Grajos)"
    },
    {
        "clave": "70650266",
        "nombre": "Trinidad de la Ley"
    },
    {
        "clave": "70650268",
        "nombre": "El Roble"
    },
    {
        "clave": "70650272",
        "nombre": "La Jahua"
    },
    {
        "clave": "70650274",
        "nombre": "San José"
    },
    {
        "clave": "70650276",
        "nombre": "La Pomarrosa"
    },
    {
        "clave": "70650277",
        "nombre": "La Loma"
    },
    {
        "clave": "70650278",
        "nombre": "San Jacobo"
    },
    {
        "clave": "70650279",
        "nombre": "Xoncoquil"
    },
    {
        "clave": "70650280",
        "nombre": "El Cambio"
    },
    {
        "clave": "70650281",
        "nombre": "Los Pollos"
    },
    {
        "clave": "70650282",
        "nombre": "Lindavista"
    },
    {
        "clave": "70650283",
        "nombre": "San Francisco"
    },
    {
        "clave": "70650285",
        "nombre": "Flor de Mayo"
    },
    {
        "clave": "70650286",
        "nombre": "San Juan"
    },
    {
        "clave": "70650287",
        "nombre": "El Barrial"
    },
    {
        "clave": "70650288",
        "nombre": "Nututún"
    },
    {
        "clave": "70650289",
        "nombre": "Paso del Cajón"
    },
    {
        "clave": "70650290",
        "nombre": "San Felipe"
    },
    {
        "clave": "70650292",
        "nombre": "El Sacrificio"
    },
    {
        "clave": "70650293",
        "nombre": "Dos Hermanos"
    },
    {
        "clave": "70650295",
        "nombre": "San Ángel"
    },
    {
        "clave": "70650298",
        "nombre": "El Remolino"
    },
    {
        "clave": "70650300",
        "nombre": "Chacamax (Santa Amalia)"
    },
    {
        "clave": "70650301",
        "nombre": "El Esfuerzo"
    },
    {
        "clave": "70650302",
        "nombre": "San José"
    },
    {
        "clave": "70650306",
        "nombre": "El Cortijo"
    },
    {
        "clave": "70650307",
        "nombre": "Santa Lucía"
    },
    {
        "clave": "70650311",
        "nombre": "Manzanares"
    },
    {
        "clave": "70650314",
        "nombre": "Nueva Esperanza"
    },
    {
        "clave": "70650315",
        "nombre": "San Miguel"
    },
    {
        "clave": "70650317",
        "nombre": "Vista Alegre"
    },
    {
        "clave": "70650320",
        "nombre": "Fracción Ocho (San Javier)"
    },
    {
        "clave": "70650322",
        "nombre": "Antonio Sánchez"
    },
    {
        "clave": "70650326",
        "nombre": "El Bajío Dos"
    },
    {
        "clave": "70650328",
        "nombre": "La Ilusión"
    },
    {
        "clave": "70650329",
        "nombre": "Jabalineros"
    },
    {
        "clave": "70650332",
        "nombre": "La Victoria"
    },
    {
        "clave": "70650333",
        "nombre": "La Herradura"
    },
    {
        "clave": "70650336",
        "nombre": "La Provincia"
    },
    {
        "clave": "70650338",
        "nombre": "La Capulina (San Miguel)"
    },
    {
        "clave": "70650340",
        "nombre": "La Crítica"
    },
    {
        "clave": "70650341",
        "nombre": "La Conquista"
    },
    {
        "clave": "70650342",
        "nombre": "La Guadalupe"
    },
    {
        "clave": "70650344",
        "nombre": "El Mangal"
    },
    {
        "clave": "70650347",
        "nombre": "El Piñal"
    },
    {
        "clave": "70650348",
        "nombre": "San Juan de Dolores"
    },
    {
        "clave": "70650350",
        "nombre": "San Fernando"
    },
    {
        "clave": "70650355",
        "nombre": "La Fragua"
    },
    {
        "clave": "70650357",
        "nombre": "El Progreso"
    },
    {
        "clave": "70650358",
        "nombre": "San Mateo"
    },
    {
        "clave": "70650359",
        "nombre": "La Gloria"
    },
    {
        "clave": "70650360",
        "nombre": "El Triunfo"
    },
    {
        "clave": "70650361",
        "nombre": "Tierra de Jehová (San Javier)"
    },
    {
        "clave": "70650363",
        "nombre": "La Victoria"
    },
    {
        "clave": "70650364",
        "nombre": "Tlampan (El Huapan)"
    },
    {
        "clave": "70650373",
        "nombre": "San Felipe 2da. Sección"
    },
    {
        "clave": "70650374",
        "nombre": "San Felipe 1ra. Sección"
    },
    {
        "clave": "70650375",
        "nombre": "Grano de Oro"
    },
    {
        "clave": "70650377",
        "nombre": "San Miguel"
    },
    {
        "clave": "70650378",
        "nombre": "La Providencia Dos"
    },
    {
        "clave": "70650379",
        "nombre": "La Fortuna"
    },
    {
        "clave": "70650380",
        "nombre": "Tres Hermanos"
    },
    {
        "clave": "70650381",
        "nombre": "San Marcos"
    },
    {
        "clave": "70650384",
        "nombre": "San Martín de Porres"
    },
    {
        "clave": "70650385",
        "nombre": "La Joya"
    },
    {
        "clave": "70650387",
        "nombre": "La Victoria"
    },
    {
        "clave": "70650388",
        "nombre": "San José"
    },
    {
        "clave": "70650390",
        "nombre": "Peor es Nada"
    },
    {
        "clave": "70650391",
        "nombre": "Santa Martha"
    },
    {
        "clave": "70650394",
        "nombre": "Brasil"
    },
    {
        "clave": "70650395",
        "nombre": "San José"
    },
    {
        "clave": "70650398",
        "nombre": "San José (La Hulera)"
    },
    {
        "clave": "70650400",
        "nombre": "La Fortuna"
    },
    {
        "clave": "70650401",
        "nombre": "San Román"
    },
    {
        "clave": "70650402",
        "nombre": "San Francisco"
    },
    {
        "clave": "70650403",
        "nombre": "El Chiapaneco"
    },
    {
        "clave": "70650406",
        "nombre": "La Terragona (San Francisco Uno)"
    },
    {
        "clave": "70650407",
        "nombre": "Palomo"
    },
    {
        "clave": "70650409",
        "nombre": "La Luz (El Rincón)"
    },
    {
        "clave": "70650410",
        "nombre": "El Pialito"
    },
    {
        "clave": "70650411",
        "nombre": "Tucumán"
    },
    {
        "clave": "70650415",
        "nombre": "El Diamante"
    },
    {
        "clave": "70650417",
        "nombre": "San Román"
    },
    {
        "clave": "70650418",
        "nombre": "La Espuela de Santa Rosa"
    },
    {
        "clave": "70650421",
        "nombre": "San Pablo"
    },
    {
        "clave": "70650422",
        "nombre": "San Martín"
    },
    {
        "clave": "70650423",
        "nombre": "San Antonio"
    },
    {
        "clave": "70650424",
        "nombre": "La Guadalupe"
    },
    {
        "clave": "70650425",
        "nombre": "El Tulipán"
    },
    {
        "clave": "70650426",
        "nombre": "Lo Veremos"
    },
    {
        "clave": "70650432",
        "nombre": "El Manguito"
    },
    {
        "clave": "70650434",
        "nombre": "Sin Nombre (Señor Encarnación)"
    },
    {
        "clave": "70650442",
        "nombre": "Santa Isabel"
    },
    {
        "clave": "70650446",
        "nombre": "La Guayabita"
    },
    {
        "clave": "70650450",
        "nombre": "San Miguel Uno"
    },
    {
        "clave": "70650451",
        "nombre": "El Piñal"
    },
    {
        "clave": "70650453",
        "nombre": "Sacrificio"
    },
    {
        "clave": "70650454",
        "nombre": "El Cocalito (Buenavista)"
    },
    {
        "clave": "70650455",
        "nombre": "La Lucha"
    },
    {
        "clave": "70650456",
        "nombre": "Santa Rosa"
    },
    {
        "clave": "70650458",
        "nombre": "San Antonio Uno"
    },
    {
        "clave": "70650459",
        "nombre": "La Majada"
    },
    {
        "clave": "70650460",
        "nombre": "El Brillante"
    },
    {
        "clave": "70650461",
        "nombre": "El Carmen Uno (Vallecillo)"
    },
    {
        "clave": "70650462",
        "nombre": "San Miguel"
    },
    {
        "clave": "70650463",
        "nombre": "San José"
    },
    {
        "clave": "70650464",
        "nombre": "La Florida"
    },
    {
        "clave": "70650468",
        "nombre": "La Guadalupe Uno"
    },
    {
        "clave": "70650472",
        "nombre": "San José de los Llanos"
    },
    {
        "clave": "70650473",
        "nombre": "La Aurora"
    },
    {
        "clave": "70650476",
        "nombre": "El Durazno"
    },
    {
        "clave": "70650481",
        "nombre": "El Carmen"
    },
    {
        "clave": "70650482",
        "nombre": "Montecristo"
    },
    {
        "clave": "70650483",
        "nombre": "San Antonio"
    },
    {
        "clave": "70650484",
        "nombre": "El Rincón"
    },
    {
        "clave": "70650485",
        "nombre": "La Carmelita"
    },
    {
        "clave": "70650487",
        "nombre": "Capulín"
    },
    {
        "clave": "70650488",
        "nombre": "El Caracol"
    },
    {
        "clave": "70650489",
        "nombre": "Guadalupe López Pérez"
    },
    {
        "clave": "70650498",
        "nombre": "El Paraíso"
    },
    {
        "clave": "70650499",
        "nombre": "Ecoparque Aluxes"
    },
    {
        "clave": "70650501",
        "nombre": "Kin-Ha"
    },
    {
        "clave": "70650504",
        "nombre": "La Argentina"
    },
    {
        "clave": "70650506",
        "nombre": "El Paraíso"
    },
    {
        "clave": "70650507",
        "nombre": "El Pan-Chan"
    },
    {
        "clave": "70650508",
        "nombre": "San Ignacio"
    },
    {
        "clave": "70650510",
        "nombre": "Kichán Bajlum"
    },
    {
        "clave": "70650515",
        "nombre": "Chan Kah"
    },
    {
        "clave": "70650520",
        "nombre": "Santa Cruz"
    },
    {
        "clave": "70650526",
        "nombre": "San José"
    },
    {
        "clave": "70650527",
        "nombre": "San Miguel"
    },
    {
        "clave": "70650531",
        "nombre": "La Guadalupe"
    },
    {
        "clave": "70650532",
        "nombre": "El Rosario"
    },
    {
        "clave": "70650534",
        "nombre": "La Guacamaya"
    },
    {
        "clave": "70650537",
        "nombre": "El Recuerdo (Las Chiapanecas)"
    },
    {
        "clave": "70650538",
        "nombre": "La Lupita"
    },
    {
        "clave": "70650540",
        "nombre": "El Treinta Y Tres"
    },
    {
        "clave": "70650541",
        "nombre": "Manolo Bernal"
    },
    {
        "clave": "70650542",
        "nombre": "Santo Domingo"
    },
    {
        "clave": "70650543",
        "nombre": "Lucinda"
    },
    {
        "clave": "70650545",
        "nombre": "El Carmen"
    },
    {
        "clave": "70650546",
        "nombre": "Santa Clara (San José)"
    },
    {
        "clave": "70650547",
        "nombre": "Tres Hermanos"
    },
    {
        "clave": "70650548",
        "nombre": "Maya Bell"
    },
    {
        "clave": "70650550",
        "nombre": "El Resbalón"
    },
    {
        "clave": "70650552",
        "nombre": "Santa Emilia"
    },
    {
        "clave": "70650553",
        "nombre": "San Antonio"
    },
    {
        "clave": "70650555",
        "nombre": "San Miguel (Tres Hermanos)"
    },
    {
        "clave": "70650558",
        "nombre": "El Sacrificio"
    },
    {
        "clave": "70650559",
        "nombre": "Ninguno"
    },
    {
        "clave": "70650560",
        "nombre": "La Victoria"
    },
    {
        "clave": "70650561",
        "nombre": "San José"
    },
    {
        "clave": "70650563",
        "nombre": "Nuevo Paraíso"
    },
    {
        "clave": "70650565",
        "nombre": "San Benito (Boca de Chak)"
    },
    {
        "clave": "70650567",
        "nombre": "Santa Adelaida"
    },
    {
        "clave": "70650570",
        "nombre": "Santa Lucrecia (Arca de Oca)"
    },
    {
        "clave": "70650571",
        "nombre": "Las Novillonas (El Sinaí)"
    },
    {
        "clave": "70650572",
        "nombre": "Rancho Verde"
    },
    {
        "clave": "70650573",
        "nombre": "El Buen Pastor"
    },
    {
        "clave": "70650576",
        "nombre": "Piñal"
    },
    {
        "clave": "70650577",
        "nombre": "El Pedregal"
    },
    {
        "clave": "70650580",
        "nombre": "Emilio Hernández"
    },
    {
        "clave": "70650581",
        "nombre": "Dos de Junio"
    },
    {
        "clave": "70650585",
        "nombre": "El Chilar"
    },
    {
        "clave": "70650588",
        "nombre": "Ciénega de Matas"
    },
    {
        "clave": "70650591",
        "nombre": "Nuevo Tila Castañón"
    },
    {
        "clave": "70650592",
        "nombre": "El Aguacate"
    },
    {
        "clave": "70650593",
        "nombre": "Montecristo"
    },
    {
        "clave": "70650594",
        "nombre": "Búfalo"
    },
    {
        "clave": "70650595",
        "nombre": "Arcoiris"
    },
    {
        "clave": "70650596",
        "nombre": "Santa Margarita"
    },
    {
        "clave": "70650597",
        "nombre": "Oxnard"
    },
    {
        "clave": "70650600",
        "nombre": "Las Gardenias"
    },
    {
        "clave": "70650601",
        "nombre": "El Dorado"
    },
    {
        "clave": "70650603",
        "nombre": "La Estrella"
    },
    {
        "clave": "70650607",
        "nombre": "San Juan"
    },
    {
        "clave": "70650613",
        "nombre": "Paso el Naranjito"
    },
    {
        "clave": "70650615",
        "nombre": "California"
    },
    {
        "clave": "70650618",
        "nombre": "Santa Rosa"
    },
    {
        "clave": "70650629",
        "nombre": "La Montura"
    },
    {
        "clave": "70650633",
        "nombre": "El Rocío"
    },
    {
        "clave": "70650634",
        "nombre": "Las Palmas"
    },
    {
        "clave": "70650636",
        "nombre": "Guadalupe"
    },
    {
        "clave": "70650637",
        "nombre": "El Mirador"
    },
    {
        "clave": "70650641",
        "nombre": "La Vaquita"
    },
    {
        "clave": "70650642",
        "nombre": "Río Seco"
    },
    {
        "clave": "70650643",
        "nombre": "Asunción Arcos"
    },
    {
        "clave": "70650644",
        "nombre": "Pascual Arcos"
    },
    {
        "clave": "70650645",
        "nombre": "La Loma"
    },
    {
        "clave": "70650646",
        "nombre": "Las Campanas"
    },
    {
        "clave": "70650647",
        "nombre": "La Lucha"
    },
    {
        "clave": "70650648",
        "nombre": "El Deseo"
    },
    {
        "clave": "70650649",
        "nombre": "Manuel Méndez Cruz"
    },
    {
        "clave": "70650650",
        "nombre": "Las Ruinas"
    },
    {
        "clave": "70650653",
        "nombre": "El Milagro"
    },
    {
        "clave": "70650654",
        "nombre": "Mi Ranchito"
    },
    {
        "clave": "70650655",
        "nombre": "El Sur de California"
    },
    {
        "clave": "70650656",
        "nombre": "La Esperanza"
    },
    {
        "clave": "70650659",
        "nombre": "Ninguno"
    },
    {
        "clave": "70650672",
        "nombre": "Crucero Chancala"
    },
    {
        "clave": "70650673",
        "nombre": "El Naranjito 1ra. Sección"
    },
    {
        "clave": "70650674",
        "nombre": "San Isidro"
    },
    {
        "clave": "70650676",
        "nombre": "La Lucha"
    },
    {
        "clave": "70650677",
        "nombre": "San Antonio el Cuyo"
    },
    {
        "clave": "70650681",
        "nombre": "Los Pérez"
    },
    {
        "clave": "70650682",
        "nombre": "Paraíso Santa Cruz"
    },
    {
        "clave": "70650687",
        "nombre": "El Cuyo Santa Cruz"
    },
    {
        "clave": "70650693",
        "nombre": "El Coleto"
    },
    {
        "clave": "70650695",
        "nombre": "La Concepción"
    },
    {
        "clave": "70650697",
        "nombre": "La Lucha"
    },
    {
        "clave": "70650699",
        "nombre": "El Durazno"
    },
    {
        "clave": "70650702",
        "nombre": "3ra. Fracción"
    },
    {
        "clave": "70650710",
        "nombre": "La Florida"
    },
    {
        "clave": "70650711",
        "nombre": "El Tazistal"
    },
    {
        "clave": "70650715",
        "nombre": "San Juan (Fracción el Desengaño)"
    },
    {
        "clave": "70650716",
        "nombre": "Santo Domingo (Fracción el Desengaño)"
    },
    {
        "clave": "70650717",
        "nombre": "San Francisco (Fracción el Desengaño)"
    },
    {
        "clave": "70650718",
        "nombre": "San Juan"
    },
    {
        "clave": "70650719",
        "nombre": "San José (Las Maromas)"
    },
    {
        "clave": "70650725",
        "nombre": "San Francisco"
    },
    {
        "clave": "70650726",
        "nombre": "Santa Priscila"
    },
    {
        "clave": "70650727",
        "nombre": "Santo Domingo"
    },
    {
        "clave": "70650730",
        "nombre": "El Caribal"
    },
    {
        "clave": "70650732",
        "nombre": "El Rubí (La Esmeralda)"
    },
    {
        "clave": "70650733",
        "nombre": "El Cincuenta (El Guayacán)"
    },
    {
        "clave": "70650734",
        "nombre": "San Miguelito"
    },
    {
        "clave": "70650735",
        "nombre": "El Zapotal"
    },
    {
        "clave": "70650737",
        "nombre": "Evangelino Pérez (San Isidro)"
    },
    {
        "clave": "70650738",
        "nombre": "Lizandro López"
    },
    {
        "clave": "70650743",
        "nombre": "Buenos Aires"
    },
    {
        "clave": "70650747",
        "nombre": "San José la Espuela"
    },
    {
        "clave": "70650752",
        "nombre": "Buenavista"
    },
    {
        "clave": "70650754",
        "nombre": "Vista Hermosa"
    },
    {
        "clave": "70650755",
        "nombre": "Agua Clara"
    },
    {
        "clave": "70650756",
        "nombre": "El Consentido"
    },
    {
        "clave": "70650757",
        "nombre": "Herlinda García G."
    },
    {
        "clave": "70650758",
        "nombre": "San Antonio"
    },
    {
        "clave": "70650759",
        "nombre": "San José"
    },
    {
        "clave": "70650762",
        "nombre": "La Galera"
    },
    {
        "clave": "70650764",
        "nombre": "Lindavista"
    },
    {
        "clave": "70650768",
        "nombre": "Pedro Peñate"
    },
    {
        "clave": "70650769",
        "nombre": "Rancho Nuevo"
    },
    {
        "clave": "70650770",
        "nombre": "Rancho Nuevo"
    },
    {
        "clave": "70650774",
        "nombre": "El Sacrificio"
    },
    {
        "clave": "70650776",
        "nombre": "Tres Arroyos"
    },
    {
        "clave": "70650777",
        "nombre": "Las Castañas"
    },
    {
        "clave": "70650778",
        "nombre": "Las Ruinas"
    },
    {
        "clave": "70650779",
        "nombre": "El Carmen"
    },
    {
        "clave": "70650780",
        "nombre": "El Carmen"
    },
    {
        "clave": "70650782",
        "nombre": "El Triunfo (Los Pinos)"
    },
    {
        "clave": "70650783",
        "nombre": "Los Leones (El Paraíso)"
    },
    {
        "clave": "70650789",
        "nombre": "San José"
    },
    {
        "clave": "70650790",
        "nombre": "Santa Trinidad"
    },
    {
        "clave": "70650799",
        "nombre": "El Progreso"
    },
    {
        "clave": "70650805",
        "nombre": "Santo Domingo"
    },
    {
        "clave": "70650806",
        "nombre": "El Esfuerzo"
    },
    {
        "clave": "70650819",
        "nombre": "San Juan"
    },
    {
        "clave": "70650821",
        "nombre": "San Antonio (La Aurora)"
    },
    {
        "clave": "70650827",
        "nombre": "El Danubio"
    },
    {
        "clave": "70650829",
        "nombre": "San José"
    },
    {
        "clave": "70650833",
        "nombre": "El Salvaje"
    },
    {
        "clave": "70650844",
        "nombre": "San José el Nanzal"
    },
    {
        "clave": "70650847",
        "nombre": "Las Víboras"
    },
    {
        "clave": "70650851",
        "nombre": "Kilómetro Trescientos Veinticinco"
    },
    {
        "clave": "70650853",
        "nombre": "San José de los Potreros"
    },
    {
        "clave": "70650854",
        "nombre": "San Manuel"
    },
    {
        "clave": "70650855",
        "nombre": "Viejo Rincón"
    },
    {
        "clave": "70650856",
        "nombre": "La Concepción"
    },
    {
        "clave": "70650857",
        "nombre": "El Miedo"
    },
    {
        "clave": "70650858",
        "nombre": "Sacrificio"
    },
    {
        "clave": "70650859",
        "nombre": "Fracción San Antonio"
    },
    {
        "clave": "70650860",
        "nombre": "San Antonio la Florida"
    },
    {
        "clave": "70650861",
        "nombre": "Las Cruces"
    },
    {
        "clave": "70650862",
        "nombre": "Cuauhtémoc Quemado"
    },
    {
        "clave": "70650864",
        "nombre": "Santo Domingo"
    },
    {
        "clave": "70650866",
        "nombre": "Los Agapos"
    },
    {
        "clave": "70650868",
        "nombre": "Santo Domingo"
    },
    {
        "clave": "70650869",
        "nombre": "Las Arboledas"
    },
    {
        "clave": "70650871",
        "nombre": "El Carmen"
    },
    {
        "clave": "70650872",
        "nombre": "San Antonio"
    },
    {
        "clave": "70650873",
        "nombre": "Las Amapolas"
    },
    {
        "clave": "70650874",
        "nombre": "El Pinal"
    },
    {
        "clave": "70650875",
        "nombre": "Santa Rita"
    },
    {
        "clave": "70650876",
        "nombre": "Tres Hermanos"
    },
    {
        "clave": "70650880",
        "nombre": "San José"
    },
    {
        "clave": "70650883",
        "nombre": "San José"
    },
    {
        "clave": "70650884",
        "nombre": "San Miguel (El Recreo Tres)"
    },
    {
        "clave": "70650886",
        "nombre": "El Limón"
    },
    {
        "clave": "70650887",
        "nombre": "Villaflores"
    },
    {
        "clave": "70650889",
        "nombre": "El Triunfo"
    },
    {
        "clave": "70650890",
        "nombre": "Santa Alicia"
    },
    {
        "clave": "70650891",
        "nombre": "Tulipán"
    },
    {
        "clave": "70650895",
        "nombre": "Guadalupe"
    },
    {
        "clave": "70650896",
        "nombre": "Los Pájaros"
    },
    {
        "clave": "70650897",
        "nombre": "El Rey"
    },
    {
        "clave": "70650898",
        "nombre": "El Varmar"
    },
    {
        "clave": "70650899",
        "nombre": "La Esperanza"
    },
    {
        "clave": "70650902",
        "nombre": "El Porvenir"
    },
    {
        "clave": "70650903",
        "nombre": "El Delirio"
    },
    {
        "clave": "70650904",
        "nombre": "El Porvenir"
    },
    {
        "clave": "70650905",
        "nombre": "San Rafael"
    },
    {
        "clave": "70650906",
        "nombre": "La Guadalupe"
    },
    {
        "clave": "70650907",
        "nombre": "El Porvenir"
    },
    {
        "clave": "70650908",
        "nombre": "Lote Número Catorce"
    },
    {
        "clave": "70650909",
        "nombre": "El Desquite"
    },
    {
        "clave": "70650911",
        "nombre": "Agua Bendita II"
    },
    {
        "clave": "70650913",
        "nombre": "La Esmeralda"
    },
    {
        "clave": "70650916",
        "nombre": "Las Trancas"
    },
    {
        "clave": "70650920",
        "nombre": "La Esperanza"
    },
    {
        "clave": "70650922",
        "nombre": "La Corcholata"
    },
    {
        "clave": "70650924",
        "nombre": "Santa Lucia"
    },
    {
        "clave": "70650926",
        "nombre": "Ninguno"
    },
    {
        "clave": "70650927",
        "nombre": "La Martinica"
    },
    {
        "clave": "70650928",
        "nombre": "San Pedro"
    },
    {
        "clave": "70650929",
        "nombre": "Cuadra San Juan"
    },
    {
        "clave": "70650954",
        "nombre": "El Zapote"
    },
    {
        "clave": "70650957",
        "nombre": "San Juanito"
    },
    {
        "clave": "70650958",
        "nombre": "La Joya"
    },
    {
        "clave": "70650960",
        "nombre": "Fracción Nueve"
    },
    {
        "clave": "70650962",
        "nombre": "El Clarín"
    },
    {
        "clave": "70650967",
        "nombre": "El Tucán"
    },
    {
        "clave": "70650975",
        "nombre": "La Esperanza"
    },
    {
        "clave": "70650986",
        "nombre": "Santa María"
    },
    {
        "clave": "70650988",
        "nombre": "El Zapote Sección Número Dos"
    },
    {
        "clave": "70650989",
        "nombre": "El Zapote"
    },
    {
        "clave": "70650994",
        "nombre": "El Rodeo"
    },
    {
        "clave": "70650996",
        "nombre": "El Zapote"
    },
    {
        "clave": "70650998",
        "nombre": "San Lorenzo"
    },
    {
        "clave": "70651001",
        "nombre": "San José"
    },
    {
        "clave": "70651002",
        "nombre": "La Providencia"
    },
    {
        "clave": "70651003",
        "nombre": "El Destino de Alvarado"
    },
    {
        "clave": "70651008",
        "nombre": "El Recreo"
    },
    {
        "clave": "70651009",
        "nombre": "Agua Clara"
    },
    {
        "clave": "70651013",
        "nombre": "El Palomar"
    },
    {
        "clave": "70651014",
        "nombre": "La Esperanza"
    },
    {
        "clave": "70651018",
        "nombre": "Crucero la Escondida"
    },
    {
        "clave": "70651019",
        "nombre": "Lindavista"
    },
    {
        "clave": "70651023",
        "nombre": "San Jesús"
    },
    {
        "clave": "70651025",
        "nombre": "Dos Hermanas"
    },
    {
        "clave": "70651026",
        "nombre": "Lomas Verde"
    },
    {
        "clave": "70651027",
        "nombre": "Agua Bendita"
    },
    {
        "clave": "70651028",
        "nombre": "Los Alazanes"
    },
    {
        "clave": "70651029",
        "nombre": "La Almendra"
    },
    {
        "clave": "70651030",
        "nombre": "Las Almendras"
    },
    {
        "clave": "70651033",
        "nombre": "La Angostura Lote Sesenta"
    },
    {
        "clave": "70651035",
        "nombre": "Los Arbolitos"
    },
    {
        "clave": "70651036",
        "nombre": "Los Arbolitos"
    },
    {
        "clave": "70651038",
        "nombre": "Balún-ke"
    },
    {
        "clave": "70651039",
        "nombre": "El Borbotón"
    },
    {
        "clave": "70651041",
        "nombre": "Buenaventura"
    },
    {
        "clave": "70651042",
        "nombre": "Las Cabras"
    },
    {
        "clave": "70651043",
        "nombre": "Calarca"
    },
    {
        "clave": "70651044",
        "nombre": "California"
    },
    {
        "clave": "70651045",
        "nombre": "El Cambio"
    },
    {
        "clave": "70651046",
        "nombre": "Isabel Aquino Casiano"
    },
    {
        "clave": "70651047",
        "nombre": "Cárdenas"
    },
    {
        "clave": "70651049",
        "nombre": "El Carmen"
    },
    {
        "clave": "70651050",
        "nombre": "La Ceiba"
    },
    {
        "clave": "70651051",
        "nombre": "El Chilar"
    },
    {
        "clave": "70651053",
        "nombre": "Arroyo Florido"
    },
    {
        "clave": "70651055",
        "nombre": "Once de Julio"
    },
    {
        "clave": "70651056",
        "nombre": "Crucero Nueva Esperanza"
    },
    {
        "clave": "70651057",
        "nombre": "Las Cruces"
    },
    {
        "clave": "70651058",
        "nombre": "Las Delicias"
    },
    {
        "clave": "70651059",
        "nombre": "Dos Hermanos"
    },
    {
        "clave": "70651063",
        "nombre": "Santa Rosa"
    },
    {
        "clave": "70651064",
        "nombre": "La Esmeralda"
    },
    {
        "clave": "70651065",
        "nombre": "La Espuela"
    },
    {
        "clave": "70651066",
        "nombre": "La Espuela"
    },
    {
        "clave": "70651067",
        "nombre": "La Espuela"
    },
    {
        "clave": "70651068",
        "nombre": "La Espuela"
    },
    {
        "clave": "70651069",
        "nombre": "El Faisán"
    },
    {
        "clave": "70651070",
        "nombre": "La Florida"
    },
    {
        "clave": "70651075",
        "nombre": "Frigorífico"
    },
    {
        "clave": "70651076",
        "nombre": "García Hermanos"
    },
    {
        "clave": "70651078",
        "nombre": "El Oeste"
    },
    {
        "clave": "70651079",
        "nombre": "Los Girasoles"
    },
    {
        "clave": "70651082",
        "nombre": "La Gravera"
    },
    {
        "clave": "70651083",
        "nombre": "La Guadalupe"
    },
    {
        "clave": "70651084",
        "nombre": "La Guadalupe (El Bajío 2da. Sección)"
    },
    {
        "clave": "70651085",
        "nombre": "El Guajuco"
    },
    {
        "clave": "70651086",
        "nombre": "El Guanal"
    },
    {
        "clave": "70651087",
        "nombre": "Los Gutiérrez"
    },
    {
        "clave": "70651088",
        "nombre": "El Habanero"
    },
    {
        "clave": "70651089",
        "nombre": "La Herradura"
    },
    {
        "clave": "70651090",
        "nombre": "La Herradura"
    },
    {
        "clave": "70651091",
        "nombre": "Los Gamos"
    },
    {
        "clave": "70651092",
        "nombre": "Hormiguero"
    },
    {
        "clave": "70651093",
        "nombre": "Las Maracas"
    },
    {
        "clave": "70651094",
        "nombre": "La Jarocha (La Guadalupana)"
    },
    {
        "clave": "70651095",
        "nombre": "Ninguno"
    },
    {
        "clave": "70651097",
        "nombre": "La Fortuna"
    },
    {
        "clave": "70651098",
        "nombre": "Lindavista"
    },
    {
        "clave": "70651099",
        "nombre": "Lindavista"
    },
    {
        "clave": "70651100",
        "nombre": "Lindavista Dos"
    },
    {
        "clave": "70651101",
        "nombre": "Lindavista"
    },
    {
        "clave": "70651104",
        "nombre": "Los Laureles"
    },
    {
        "clave": "70651105",
        "nombre": "Michoacán"
    },
    {
        "clave": "70651106",
        "nombre": "Los Monos"
    },
    {
        "clave": "70651110",
        "nombre": "La Natividad"
    },
    {
        "clave": "70651114",
        "nombre": "Nuevo Progreso"
    },
    {
        "clave": "70651116",
        "nombre": "Nuevo San Leandro"
    },
    {
        "clave": "70651117",
        "nombre": "Los Ángeles"
    },
    {
        "clave": "70651118",
        "nombre": "Ojo de Agua"
    },
    {
        "clave": "70651119",
        "nombre": "Ojo de Agua"
    },
    {
        "clave": "70651120",
        "nombre": "Las Palmas"
    },
    {
        "clave": "70651121",
        "nombre": "Las Palmas"
    },
    {
        "clave": "70651123",
        "nombre": "El Paraíso"
    },
    {
        "clave": "70651125",
        "nombre": "Pedregal del Chacamax"
    },
    {
        "clave": "70651126",
        "nombre": "El Pedregal"
    },
    {
        "clave": "70651128",
        "nombre": "Piedras Negras (La Balanza)"
    },
    {
        "clave": "70651129",
        "nombre": "Los Pinos"
    },
    {
        "clave": "70651130",
        "nombre": "El Plebeyo"
    },
    {
        "clave": "70651132",
        "nombre": "El Porvenir"
    },
    {
        "clave": "70651133",
        "nombre": "El Potrillo"
    },
    {
        "clave": "70651134",
        "nombre": "Los Pozuelos"
    },
    {
        "clave": "70651135",
        "nombre": "La Lupita"
    },
    {
        "clave": "70651136",
        "nombre": "La Protegida"
    },
    {
        "clave": "70651137",
        "nombre": "La Provincia"
    },
    {
        "clave": "70651139",
        "nombre": "Rancho Nuevo"
    },
    {
        "clave": "70651140",
        "nombre": "El Recuerdo"
    },
    {
        "clave": "70651141",
        "nombre": "El Recuerdo"
    },
    {
        "clave": "70651142",
        "nombre": "El Recuerdo"
    },
    {
        "clave": "70651143",
        "nombre": "El Retazo"
    },
    {
        "clave": "70651148",
        "nombre": "El Sacrificio"
    },
    {
        "clave": "70651149",
        "nombre": "El Sacrificio"
    },
    {
        "clave": "70651150",
        "nombre": "El Sacrificio"
    },
    {
        "clave": "70651153",
        "nombre": "San Antonio"
    },
    {
        "clave": "70651155",
        "nombre": "Cheboya"
    },
    {
        "clave": "70651157",
        "nombre": "San Cristóbal"
    },
    {
        "clave": "70651158",
        "nombre": "San Cristóbal"
    },
    {
        "clave": "70651159",
        "nombre": "San Mateo"
    },
    {
        "clave": "70651160",
        "nombre": "San Francisco"
    },
    {
        "clave": "70651161",
        "nombre": "San Francisco"
    },
    {
        "clave": "70651162",
        "nombre": "San Francisco"
    },
    {
        "clave": "70651163",
        "nombre": "San Francisco"
    },
    {
        "clave": "70651164",
        "nombre": "San Miguel"
    },
    {
        "clave": "70651165",
        "nombre": "San Isidro"
    },
    {
        "clave": "70651166",
        "nombre": "San José"
    },
    {
        "clave": "70651167",
        "nombre": "San José"
    },
    {
        "clave": "70651168",
        "nombre": "San José"
    },
    {
        "clave": "70651171",
        "nombre": "San José"
    },
    {
        "clave": "70651172",
        "nombre": "San Juan Chocolja"
    },
    {
        "clave": "70651175",
        "nombre": "San Miguel"
    },
    {
        "clave": "70651178",
        "nombre": "San Pedro"
    },
    {
        "clave": "70651180",
        "nombre": "Las Palmas"
    },
    {
        "clave": "70651181",
        "nombre": "San Rafael"
    },
    {
        "clave": "70651182",
        "nombre": "San Román"
    },
    {
        "clave": "70651183",
        "nombre": "San Román"
    },
    {
        "clave": "70651184",
        "nombre": "San Roque"
    },
    {
        "clave": "70651185",
        "nombre": "Santa Alicia"
    },
    {
        "clave": "70651186",
        "nombre": "Santa Eloísa"
    },
    {
        "clave": "70651188",
        "nombre": "Santa Isabel"
    },
    {
        "clave": "70651189",
        "nombre": "Santa Juanita"
    },
    {
        "clave": "70651190",
        "nombre": "Los Corazones"
    },
    {
        "clave": "70651191",
        "nombre": "Santa Martha"
    },
    {
        "clave": "70651192",
        "nombre": "Santa Rosa"
    },
    {
        "clave": "70651193",
        "nombre": "Santa Rosa"
    },
    {
        "clave": "70651194",
        "nombre": "Santa Rosa"
    },
    {
        "clave": "70651195",
        "nombre": "Santa Teresa"
    },
    {
        "clave": "70651196",
        "nombre": "Santo Domingo"
    },
    {
        "clave": "70651197",
        "nombre": "Santo Tomás"
    },
    {
        "clave": "70651198",
        "nombre": "Fracción Santo Tomás"
    },
    {
        "clave": "70651200",
        "nombre": "Localidad Sin Nombre"
    },
    {
        "clave": "70651204",
        "nombre": "San Juan"
    },
    {
        "clave": "70651205",
        "nombre": "Paraíso Maya Palenque"
    },
    {
        "clave": "70651206",
        "nombre": "Sin Nombre (Audias Bernal)"
    },
    {
        "clave": "70651207",
        "nombre": "Rancho San Antonio"
    },
    {
        "clave": "70651208",
        "nombre": "Isidora Ascencio"
    },
    {
        "clave": "70651209",
        "nombre": "Juan Alejo"
    },
    {
        "clave": "70651210",
        "nombre": "Ignacio"
    },
    {
        "clave": "70651211",
        "nombre": "Mariano Mora Huerta"
    },
    {
        "clave": "70651212",
        "nombre": "Los Laureles"
    },
    {
        "clave": "70651214",
        "nombre": "El Triunfo"
    },
    {
        "clave": "70651215",
        "nombre": "Río Chacamax"
    },
    {
        "clave": "70651216",
        "nombre": "Terranova"
    },
    {
        "clave": "70651217",
        "nombre": "La Tijera"
    },
    {
        "clave": "70651219",
        "nombre": "Los Tres Hermanos"
    },
    {
        "clave": "70651221",
        "nombre": "El Triunfo"
    },
    {
        "clave": "70651223",
        "nombre": "La Unión"
    },
    {
        "clave": "70651224",
        "nombre": "El Venado Blanco"
    },
    {
        "clave": "70651226",
        "nombre": "Victoria Campesina II"
    },
    {
        "clave": "70651229",
        "nombre": "Esperanza"
    },
    {
        "clave": "70651231",
        "nombre": "Once de Julio"
    },
    {
        "clave": "70651233",
        "nombre": "Sin Nombre (Dionisio Pérez Ballinas)"
    },
    {
        "clave": "70651234",
        "nombre": "Sin Nombre (Fausto Cruz Méndez)"
    },
    {
        "clave": "70651235",
        "nombre": "Sin Nombre (Gonzalo Mendoza Gómez)"
    },
    {
        "clave": "70651236",
        "nombre": "Sin Nombre (Magdalena Hurtado Sánchez)"
    },
    {
        "clave": "70651237",
        "nombre": "Sin Nombre (Pablo Sánchez)"
    },
    {
        "clave": "70651238",
        "nombre": "Sin Nombre (Roberto Pinto López)"
    },
    {
        "clave": "70651241",
        "nombre": "Aquí me Quedo"
    },
    {
        "clave": "70651245",
        "nombre": "Chaac"
    },
    {
        "clave": "70651246",
        "nombre": "La Escalera"
    },
    {
        "clave": "70651247",
        "nombre": "La Esperanza"
    },
    {
        "clave": "70651249",
        "nombre": "Santa Rosa"
    },
    {
        "clave": "70651251",
        "nombre": "Fracción Manga de Clavo"
    },
    {
        "clave": "70651253",
        "nombre": "El Fresnito"
    },
    {
        "clave": "70651254",
        "nombre": "Jazmín"
    },
    {
        "clave": "70651255",
        "nombre": "Juan Aldama"
    },
    {
        "clave": "70651257",
        "nombre": "El Manantial"
    },
    {
        "clave": "70651258",
        "nombre": "Muzquiz"
    },
    {
        "clave": "70651261",
        "nombre": "La Orilla"
    },
    {
        "clave": "70651262",
        "nombre": "El Pirata"
    },
    {
        "clave": "70651263",
        "nombre": "El Roble"
    },
    {
        "clave": "70651264",
        "nombre": "El Sacrificio"
    },
    {
        "clave": "70651265",
        "nombre": "San Agustín"
    },
    {
        "clave": "70651266",
        "nombre": "San Antonio Dos"
    },
    {
        "clave": "70651267",
        "nombre": "San Carlos"
    },
    {
        "clave": "70651269",
        "nombre": "San Luis"
    },
    {
        "clave": "70651270",
        "nombre": "Santa Margarita"
    },
    {
        "clave": "70651271",
        "nombre": "El Suspiro"
    },
    {
        "clave": "70651272",
        "nombre": "San Rafael"
    },
    {
        "clave": "70651273",
        "nombre": "San Juan (José Manuel Lastra)"
    },
    {
        "clave": "70651274",
        "nombre": "Rancho 3 Hermanos"
    },
    {
        "clave": "70651275",
        "nombre": "Eugenio Hernández"
    },
    {
        "clave": "70651276",
        "nombre": "Vicente Román Lezama"
    },
    {
        "clave": "70651280",
        "nombre": "Anover"
    },
    {
        "clave": "70651281",
        "nombre": "Bethel"
    },
    {
        "clave": "70651284",
        "nombre": "La Bonita"
    },
    {
        "clave": "70651285",
        "nombre": "Ulolyakún-Ha"
    },
    {
        "clave": "70651288",
        "nombre": "El Lago"
    },
    {
        "clave": "70651290",
        "nombre": "La Paila"
    },
    {
        "clave": "70651292",
        "nombre": "La Primavera"
    },
    {
        "clave": "70651293",
        "nombre": "La Providencia"
    },
    {
        "clave": "70651294",
        "nombre": "El Roble"
    },
    {
        "clave": "70651298",
        "nombre": "Saturnino Ríos 2da. Sección San Antonio"
    },
    {
        "clave": "70651299",
        "nombre": "Localidad sin Nombre (Carlos Pashid)"
    },
    {
        "clave": "70651300",
        "nombre": "El Capulín"
    },
    {
        "clave": "70651306",
        "nombre": "El Capulin"
    },
    {
        "clave": "70651312",
        "nombre": "Las Malvinas (Santa Isabel)"
    },
    {
        "clave": "70651313",
        "nombre": "Niños Heroes"
    },
    {
        "clave": "70651319",
        "nombre": "La Palma"
    },
    {
        "clave": "70651320",
        "nombre": "Rancho Viejo (4 Hermanos)"
    },
    {
        "clave": "70651322",
        "nombre": "El Torete"
    },
    {
        "clave": "70651325",
        "nombre": "Rancho Santos Aguilar Vázquez"
    },
    {
        "clave": "70651326",
        "nombre": "El Mariché"
    },
    {
        "clave": "70651327",
        "nombre": "Brisas del Chacamax"
    },
    {
        "clave": "70651328",
        "nombre": "El Relicario"
    },
    {
        "clave": "70651329",
        "nombre": "San Agustín"
    },
    {
        "clave": "70651330",
        "nombre": "La Sombra"
    },
    {
        "clave": "70651331",
        "nombre": "Valparaíso"
    },
    {
        "clave": "70651332",
        "nombre": "Los Ángeles"
    },
    {
        "clave": "70651333",
        "nombre": "El Gayacán"
    },
    {
        "clave": "70651334",
        "nombre": "El Caracol"
    },
    {
        "clave": "70651338",
        "nombre": "El Pial"
    },
    {
        "clave": "70651339",
        "nombre": "El Retiro"
    },
    {
        "clave": "70651340",
        "nombre": "San Antonio"
    },
    {
        "clave": "70651341",
        "nombre": "San Francisco"
    },
    {
        "clave": "70651345",
        "nombre": "La Aldea"
    },
    {
        "clave": "70651346",
        "nombre": "Buenavista del Rosario"
    },
    {
        "clave": "70651347",
        "nombre": "Las Campanas"
    },
    {
        "clave": "70651349",
        "nombre": "La Guadalupe"
    },
    {
        "clave": "70651350",
        "nombre": "José María Morelos Y Pavón"
    },
    {
        "clave": "70651352",
        "nombre": "Quiloma Ranch"
    },
    {
        "clave": "70651353",
        "nombre": "Las Mercedes"
    },
    {
        "clave": "70651354",
        "nombre": "Nuevo Chapultepec"
    },
    {
        "clave": "70651356",
        "nombre": "El Paraíso"
    },
    {
        "clave": "70651358",
        "nombre": "Santa Rosa"
    },
    {
        "clave": "70651360",
        "nombre": "El Espejo Uno"
    },
    {
        "clave": "70651361",
        "nombre": "Jericó"
    },
    {
        "clave": "70651362",
        "nombre": "Nuevo Jerusalén"
    },
    {
        "clave": "70651363",
        "nombre": "Poblado 30 de Marzo"
    },
    {
        "clave": "70651364",
        "nombre": "Río Usumacinta"
    },
    {
        "clave": "70651365",
        "nombre": "El Pital"
    },
    {
        "clave": "70651366",
        "nombre": "El Tigrillo"
    },
    {
        "clave": "70651367",
        "nombre": "San Hipólito"
    },
    {
        "clave": "70651368",
        "nombre": "El Naranjo"
    },
    {
        "clave": "70651369",
        "nombre": "Emilio Corzo Blanco"
    },
    {
        "clave": "70651370",
        "nombre": "Brisas del Chacamax"
    },
    {
        "clave": "70651371",
        "nombre": "El Recuerdo"
    },
    {
        "clave": "70651373",
        "nombre": "El Porvenir"
    },
    {
        "clave": "70651382",
        "nombre": "Morelos"
    },
    {
        "clave": "70651383",
        "nombre": "El Cortijo"
    },
    {
        "clave": "70651384",
        "nombre": "Antonio Huerta"
    },
    {
        "clave": "70651385",
        "nombre": "Los Cascabeles"
    },
    {
        "clave": "70651386",
        "nombre": "Los Laureles"
    },
    {
        "clave": "70651387",
        "nombre": "Santa Lucrecia"
    },
    {
        "clave": "70651388",
        "nombre": "Nuevo Progreso"
    },
    {
        "clave": "70651390",
        "nombre": "El Cajón"
    },
    {
        "clave": "70651391",
        "nombre": "El Colibrí"
    },
    {
        "clave": "70651392",
        "nombre": "El Paraíso"
    },
    {
        "clave": "70651393",
        "nombre": "Kan-Kan-Há"
    },
    {
        "clave": "70651396",
        "nombre": "Lote 53"
    },
    {
        "clave": "70651397",
        "nombre": "Olga Segura"
    },
    {
        "clave": "70651398",
        "nombre": "Sal Sipuedes"
    },
    {
        "clave": "70651399",
        "nombre": "San Jorge"
    },
    {
        "clave": "70651401",
        "nombre": "Linda Vista"
    },
    {
        "clave": "70651402",
        "nombre": "Venustiano Carranza"
    },
    {
        "clave": "70651403",
        "nombre": "Los Huayacanes"
    },
    {
        "clave": "70651404",
        "nombre": "Rancho Viejo"
    },
    {
        "clave": "70651405",
        "nombre": "El Desengaño"
    },
    {
        "clave": "70651406",
        "nombre": "Vista Alegre"
    },
    {
        "clave": "70651410",
        "nombre": "Las Potrancas"
    },
    {
        "clave": "70651412",
        "nombre": "La Báscula"
    },
    {
        "clave": "70651414",
        "nombre": "Santa Lucía"
    },
    {
        "clave": "70651415",
        "nombre": "El Carmen"
    },
    {
        "clave": "70651418",
        "nombre": "La Flor de la Papaya"
    },
    {
        "clave": "70651419",
        "nombre": "Los Saucitos"
    },
    {
        "clave": "70651420",
        "nombre": "Trébol"
    },
    {
        "clave": "70651421",
        "nombre": "Trébol"
    },
    {
        "clave": "70651423",
        "nombre": "Paraíso el Dorante"
    },
    {
        "clave": "70651424",
        "nombre": "Los Potrillos"
    },
    {
        "clave": "70651425",
        "nombre": "Paraíso"
    },
    {
        "clave": "70651426",
        "nombre": "Belem"
    },
    {
        "clave": "70651427",
        "nombre": "La Parota"
    },
    {
        "clave": "70651428",
        "nombre": "Revolución Segunda Sección"
    },
    {
        "clave": "70651429",
        "nombre": "Los Rieles del Paraíso"
    }
]