[
    {
        "clave": "140570002",
        "nombre": "El Aguacate (La Sabanilla)"
    },
    {
        "clave": "140570012",
        "nombre": "Sabinilla"
    },
    {
        "clave": "140570014",
        "nombre": "La Tuna"
    },
    {
        "clave": "140570001",
        "nombre": "La Manzanilla de la Paz"
    },
    {
        "clave": "140570003",
        "nombre": "Las Cuevas"
    },
    {
        "clave": "140570006",
        "nombre": "Loma Alta"
    },
    {
        "clave": "140570007",
        "nombre": "Llano Colorado"
    },
    {
        "clave": "140570008",
        "nombre": "La Mota"
    },
    {
        "clave": "140570010",
        "nombre": "Regladero"
    },
    {
        "clave": "140570013",
        "nombre": "La Soledad"
    },
    {
        "clave": "140570015",
        "nombre": "Las Verdolagas"
    },
    {
        "clave": "140570016",
        "nombre": "Villa Morelos"
    },
    {
        "clave": "140570018",
        "nombre": "La Atarjea"
    },
    {
        "clave": "140570019",
        "nombre": "Tienda Nueva"
    },
    {
        "clave": "140570021",
        "nombre": "Casa de Altos (La Soledad)"
    },
    {
        "clave": "140570022",
        "nombre": "El Rincón"
    },
    {
        "clave": "140570024",
        "nombre": "Prolongación Lázaro Cárdenas (El Regadillo)"
    },
    {
        "clave": "140570026",
        "nombre": "Agua Escondida"
    },
    {
        "clave": "140570027",
        "nombre": "La Atarjea (Los Corrales)"
    },
    {
        "clave": "140570028",
        "nombre": "La Becerrera"
    },
    {
        "clave": "140570029",
        "nombre": "El Capulín (Los Corrales)"
    },
    {
        "clave": "140570030",
        "nombre": "El Carretón"
    },
    {
        "clave": "140570031",
        "nombre": "La Lajita"
    },
    {
        "clave": "140570032",
        "nombre": "Las Lomas"
    },
    {
        "clave": "140570033",
        "nombre": "Mesa del Hoyanco"
    },
    {
        "clave": "140570034",
        "nombre": "Palos Altos"
    },
    {
        "clave": "140570035",
        "nombre": "Rancho Santa María"
    },
    {
        "clave": "140570036",
        "nombre": "El Retoñal"
    },
    {
        "clave": "140570037",
        "nombre": "Sabinilla de Abajo"
    },
    {
        "clave": "140570038",
        "nombre": "San Rafael"
    },
    {
        "clave": "140570039",
        "nombre": "El Palo Herrado"
    },
    {
        "clave": "140570040",
        "nombre": "Colonia San Rafael"
    }
]