[
    {
        "clave": "204210011",
        "nombre": "Nizabiguidi"
    },
    {
        "clave": "204210001",
        "nombre": "Santa María Mixtequilla"
    },
    {
        "clave": "204210003",
        "nombre": "Kilómetro 10 Nizzapipi (San Antonio)"
    },
    {
        "clave": "204210005",
        "nombre": "El Sauce"
    },
    {
        "clave": "204210008",
        "nombre": "La Cantera"
    },
    {
        "clave": "204210010",
        "nombre": "La Alcantarilla"
    },
    {
        "clave": "204210016",
        "nombre": "Santa Teresa de Jesús"
    },
    {
        "clave": "204210006",
        "nombre": "Presa las Pilas"
    },
    {
        "clave": "204210007",
        "nombre": "El Potrerillo"
    },
    {
        "clave": "204210009",
        "nombre": "Frontera Sur"
    },
    {
        "clave": "204210012",
        "nombre": "Paso Lagarto"
    },
    {
        "clave": "204210013",
        "nombre": "Rancho Conrado"
    },
    {
        "clave": "204210014",
        "nombre": "Barrio Nuevo"
    },
    {
        "clave": "204210015",
        "nombre": "Colonia San Antonio"
    },
    {
        "clave": "204210017",
        "nombre": "Punto los Amates"
    },
    {
        "clave": "204210018",
        "nombre": "Las Cuevas"
    }
]